imagekitio/__init__.py
imagekitio/_base_client.py
imagekitio/_client.py
imagekitio/_compat.py
imagekitio/_constants.py
imagekitio/_exceptions.py
imagekitio/_files.py
imagekitio/_models.py
imagekitio/_qs.py
imagekitio/_resource.py
imagekitio/_response.py
imagekitio/_streaming.py
imagekitio/_types.py
imagekitio/_version.py
imagekitio/py.typed
imagekitio/_utils/__init__.py
imagekitio/_utils/_compat.py
imagekitio/_utils/_datetime_parse.py
imagekitio/_utils/_logs.py
imagekitio/_utils/_proxy.py
imagekitio/_utils/_reflection.py
imagekitio/_utils/_resources_proxy.py
imagekitio/_utils/_streams.py
imagekitio/_utils/_sync.py
imagekitio/_utils/_transform.py
imagekitio/_utils/_typing.py
imagekitio/_utils/_utils.py
imagekitio/lib/.keep
imagekitio/lib/__init__.py
imagekitio/lib/helper.py
imagekitio/lib/serialization_utils.py
imagekitio/resources/__init__.py
imagekitio/resources/assets.py
imagekitio/resources/custom_metadata_fields.py
imagekitio/resources/dummy.py
imagekitio/resources/saved_extensions.py
imagekitio/resources/webhooks.py
imagekitio/resources/accounts/__init__.py
imagekitio/resources/accounts/accounts.py
imagekitio/resources/accounts/origins.py
imagekitio/resources/accounts/url_endpoints.py
imagekitio/resources/accounts/usage.py
imagekitio/resources/beta/__init__.py
imagekitio/resources/beta/beta.py
imagekitio/resources/beta/v2/__init__.py
imagekitio/resources/beta/v2/files.py
imagekitio/resources/beta/v2/v2.py
imagekitio/resources/cache/__init__.py
imagekitio/resources/cache/cache.py
imagekitio/resources/cache/invalidation.py
imagekitio/resources/files/__init__.py
imagekitio/resources/files/bulk.py
imagekitio/resources/files/files.py
imagekitio/resources/files/metadata.py
imagekitio/resources/files/versions.py
imagekitio/resources/folders/__init__.py
imagekitio/resources/folders/folders.py
imagekitio/resources/folders/job.py
imagekitio/types/__init__.py
imagekitio/types/asset_list_params.py
imagekitio/types/asset_list_response.py
imagekitio-5.1.1.dist-info/METADATA
imagekitio-5.1.1.dist-info/WHEEL
imagekitio-5.1.1.dist-info/licenses/LICENSE
imagekitio-5.1.1.dist-info/RECORD
